{
  "_meta": {
    "description": "Ground truth for the fixture screenshots in this directory. HP percentages were measured manually and pixel-exactly (fill-run width on the bar's middle row / 218 px total inner bar width, see scripts/measure_fill.py); they are independent of the production reader. Tests must compare HP with the tolerance below.",
    "hp_tolerance_pct": 3.0,
    "bar_inner_width_px": 218,
    "bar_note": "The PokeMMO battle UI is rendered at a fixed pixel size: the enemy HP bar's inner width is 218 px in every fixture, including 1920x1080_resolution.png. The empty part of the bar is white with a diagonal crosshatch pattern, not dark.",
    "location_note": "location is the HUD text top-left without the ' Ch. N' channel suffix.",
    "scenes": ["overworld", "wild_single", "wild_double", "trainer"],
    "statuses": ["none", "slp", "par", "psn", "brn", "frz"],
    "status_badge_note": "Status badge sits left of the enemy name: SLP = gray 'Z', PAR = yellow lightning, PSN = purple skull (from full_health_trainer_battle_poisoned.png). BRN/FRZ have no fixture yet.",
    "stat_stage_note": "Some fixtures show an orange stat-stage box (e.g. '-1 Atk', '-2 Eva') to the right of the enemy HP bar. It is game UI for stat changes and must not disturb HP/status reading."
  },
  "fixtures": {
    "full_health_no_status.png": {
      "scene": "wild_single",
      "location": "Eterna Forest",
      "overlay_visible": true,
      "enemies": [
        { "name": "Cascoon", "level": 11, "hp_pct": 100.0, "hp_color": "green", "status": "none" }
      ]
    },
    "full_health_sleeping.png": {
      "scene": "wild_single",
      "location": "Eterna Forest",
      "overlay_visible": true,
      "enemies": [
        { "name": "Cascoon", "level": 11, "hp_pct": 100.0, "hp_color": "green", "status": "slp" }
      ],
      "notes": "Game window is smaller than in the other Eterna fixtures; Windows taskbar visible at the bottom."
    },
    "full_health_paralyzed.png": {
      "scene": "wild_single",
      "location": "Eterna Forest",
      "overlay_visible": true,
      "enemies": [
        { "name": "Cascoon", "level": 11, "hp_pct": 100.0, "hp_color": "green", "status": "par" }
      ]
    },
    "full_health_water.png": {
      "scene": "wild_single",
      "location": "Route 41",
      "overlay_visible": true,
      "enemies": [
        { "name": "Mantine", "level": 22, "hp_pct": 100.0, "hp_color": "green", "status": "none" }
      ],
      "notes": "Water battle; 'IronPixxelX sent out Smeargle!' textbox visible."
    },
    "two_third_green_health_cave.png": {
      "scene": "wild_single",
      "location": "Victory Road",
      "overlay_visible": true,
      "enemies": [
        { "name": "Onix", "level": 43, "hp_pct": 65.1, "hp_color": "green", "status": "none" }
      ],
      "notes": "Move-selection submenu open; sandstorm haze over the scene."
    },
    "two_third_green_health_sleeping_cave.png": {
      "scene": "wild_single",
      "location": "Victory Road",
      "overlay_visible": true,
      "enemies": [
        { "name": "Onix", "level": 43, "hp_pct": 65.1, "hp_color": "green", "status": "slp" }
      ],
      "notes": "'The sandstorm rages' textbox visible."
    },
    "yellow_health_no_status_cave.png": {
      "scene": "wild_single",
      "location": "Victory Road",
      "overlay_visible": true,
      "enemies": [
        { "name": "Onix", "level": 43, "hp_pct": 41.7, "hp_color": "yellow", "status": "none" }
      ],
      "notes": "Orange '-2 Eva' stat-stage box right of the HP bar."
    },
    "yellow_health_sleeping_cave.png": {
      "scene": "wild_single",
      "location": "Victory Road",
      "overlay_visible": true,
      "enemies": [
        { "name": "Onix", "level": 43, "hp_pct": 47.2, "hp_color": "yellow", "status": "slp" }
      ]
    },
    "red_health_no_status_cave.png": {
      "scene": "wild_single",
      "location": "Victory Road",
      "overlay_visible": true,
      "enemies": [
        { "name": "Onix", "level": 43, "hp_pct": 4.6, "hp_color": "red", "status": "none" }
      ],
      "notes": "Orange stat-stage box right of the HP bar."
    },
    "red_health_sleeping_cave.png": {
      "scene": "wild_single",
      "location": "Victory Road",
      "overlay_visible": true,
      "enemies": [
        { "name": "Onix", "level": 43, "hp_pct": 4.6, "hp_color": "red", "status": "slp" }
      ]
    },
    "1_HP_red_health_no_status_cave.png": {
      "scene": "wild_single",
      "location": "Victory Road",
      "overlay_visible": true,
      "enemies": [
        { "name": "Ursaring", "level": 40, "hp_pct": 1.0, "hp_color": "red", "status": "none" }
      ],
      "notes": "Exactly 1 HP; fill is a 2-3 px sliver. Reader must report a value > 0."
    },
    "1_HP_red_health_sleeping_cave.png": {
      "scene": "wild_single",
      "location": "Victory Road",
      "overlay_visible": true,
      "enemies": [
        { "name": "Ursaring", "level": 40, "hp_pct": 1.0, "hp_color": "red", "status": "slp" }
      ],
      "notes": "Exactly 1 HP; fill is a 2-3 px sliver. Reader must report a value > 0."
    },
    "red_health_paralyzed.png": {
      "scene": "wild_double",
      "location": "Route 205",
      "overlay_visible": false,
      "enemies": [
        { "name": "Cherubi", "level": 17, "hp_pct": 11.5, "hp_color": "red", "status": "par" }
      ],
      "notes": "Double battle with one enemy already fainted: one enemy bar left, but two ally bars (Rotom, Staravia) visible. v1 ignores double battles."
    },
    "double_battle_no_status.png": {
      "scene": "wild_double",
      "location": "Route 205",
      "overlay_visible": false,
      "enemies": [
        { "name": "Combee", "level": 16, "hp_pct": 100.0, "hp_color": "green", "status": "none" },
        { "name": "Cherubi", "level": 17, "hp_pct": 100.0, "hp_color": "green", "status": "none" }
      ],
      "notes": "Two stacked enemy bars; orange '-1 Atk' stat-stage box next to each."
    },
    "full_health_trainer_battle_no_status.png": {
      "scene": "trainer",
      "location": "Route 205",
      "overlay_visible": false,
      "enemies": [
        { "name": "Ponyta", "level": 14, "hp_pct": 100.0, "hp_color": "green", "status": "none" }
      ]
    },
    "full_health_trainer_battle_poisoned.png": {
      "scene": "trainer",
      "location": "Route 205",
      "overlay_visible": false,
      "enemies": [
        { "name": "Pachirisu", "level": 12, "hp_pct": 100.0, "hp_color": "green", "status": "psn" }
      ],
      "notes": "Enemy poisoned at full HP (purple skull badge). Own Roserade also has a status badge."
    },
    "overworld_city_biking.png": {
      "scene": "overworld",
      "location": "Floaroma Town",
      "overlay_visible": false,
      "enemies": [],
      "notes": "Player on bike."
    },
    "overworld_city_running.png": {
      "scene": "overworld",
      "location": "Floaroma Town",
      "overlay_visible": false,
      "enemies": []
    },
    "overworld_wild_running.png": {
      "scene": "overworld",
      "location": "Route 205",
      "overlay_visible": false,
      "enemies": [],
      "notes": "On a route with wild grass nearby; still no battle UI."
    },
    "1920x1080_resolution.png": {
      "scene": "wild_single",
      "location": "Route 41",
      "overlay_visible": true,
      "enemies": [
        { "name": "Tentacool", "level": 24, "hp_pct": 100.0, "hp_color": "green", "status": "none" }
      ],
      "notes": "1920x1080 client resolution; battle UI elements keep their fixed pixel size (bar still 218 px)."
    },
    "login_screen.png": {
      "scene": "login",
      "location": null,
      "overlay_visible": false,
      "enemies": [],
      "notes": "PokeMMO login screen (dark Zekrom over a light backdrop). Has no enemy HP bar; must NOT be detected as a battle even though dark pixels exist in the bottom region."
    }
  },
  "_action_fixtures_note": "Single battle frames captured at the moment an action resolves, for the turn counter (milestone 2). A turn is counted only when a committed-action textbox appears (not when the menu merely closes, e.g. BAG -> cancel). Battle text shows bottom-left of the viewport. Filenames keep the user's spelling ('batle_').",
  "action_fixtures": {
    "batle_action_attack_selected.png": {
      "action": "attack",
      "battle_text": "Monferno used Ember!",
      "ends_battle": false
    },
    "batle_action_item_selected.png": {
      "action": "item",
      "battle_text": "IronPixxelX used the Ether (PP).",
      "ends_battle": false
    },
    "batle_action_pokemon_switch.png": {
      "action": "switch",
      "battle_text": "Monferno, OK! Come back!",
      "ends_battle": false
    },
    "batle_action_pokeball_thrown.png": {
      "action": "ball",
      "battle_text": null,
      "ends_battle": false,
      "notes": "Pokeball mid-throw animation; no textbox in this frame."
    },
    "batle_action_run_selected.png": {
      "action": "run",
      "battle_text": "Got away safely!",
      "ends_battle": true,
      "notes": "Fleeing actively ends the battle."
    }
  },
  "_chat_minimized_note": "Battle frames captured right after an attack animation with the chat minimized, at different window sizes. These show the in-viewport narration textbox (which would be the only turn cue with the chat hidden) and confirm the HP-bar vanish/return behaviour: during the zoom/attack animation the enemy HP bar is gone (frame 1), and it reappears just after (frames 2-4). The turn counter's chat-independent fallback keys on that vanish/return cycle. 'bar_visible' is whether read_enemy_bars should find the enemy HP bar in this exact frame.",
  "chat_minimized_fixtures": {
    "batle_action_attack_chat_minimized_1.png": {
      "battle_text": "Lucario used Aura Sphere!",
      "bar_visible": false,
      "notes": "Mid attack animation; HP bar hidden."
    },
    "batle_action_attack_chat_minimized_2.png": {
      "battle_text": "It's super effective!",
      "bar_visible": true,
      "enemy": "Marill"
    },
    "batle_action_attack_chat_minimized_3.png": {
      "battle_text": "Roserade used Toxic Spikes!",
      "bar_visible": true,
      "enemy": "Krokorok"
    },
    "batle_action_attack_chat_minimized_4.png": {
      "battle_text": "Roserade used Venoshock!",
      "bar_visible": true,
      "enemy": "Krokorok"
    }
  },
  "_catch_fixtures_note": "Frames from a successful capture. The catch is detected from the chat log line 'Gotcha! X was caught!' (read_chat.caught), which also ends the battle once the enemy bar is gone.",
  "catch_fixtures": {
    "batle_action_pokemon_catched_dark_pokeballpng.png": {
      "phase": "ball_on_field",
      "caught_text": false,
      "notes": "Pokeball resting on the field; enemy sprite replaced by the ball, enemy HP bar still shown, no catch text yet."
    },
    "batle_action_pokemon_catched_text_after pokeball_disapeared.png": {
      "phase": "caught_confirmed",
      "caught_text": true,
      "notes": "In-viewport and chat show 'Gotcha! ... was caught!'."
    }
  }
}
